__init__.py
registry.py
server.py
iflow_mcp_gustavo_meilus_logseq_api_mcp-0.1.0.dist-info/licenses/LICENSE
tools/__init__.py
tools/append_block_in_page.py
tools/create_page.py
tools/edit_block.py
tools/get_all_page_content.py
tools/get_all_pages.py
tools/get_block_content.py
tools/get_linked_flashcards.py
tools/get_page_blocks.py
tools/get_page_links.py
iflow_mcp_gustavo_meilus_logseq_api_mcp-0.1.0.dist-info/METADATA
iflow_mcp_gustavo_meilus_logseq_api_mcp-0.1.0.dist-info/WHEEL
iflow_mcp_gustavo_meilus_logseq_api_mcp-0.1.0.dist-info/entry_points.txt
iflow_mcp_gustavo_meilus_logseq_api_mcp-0.1.0.dist-info/top_level.txt
iflow_mcp_gustavo_meilus_logseq_api_mcp-0.1.0.dist-info/RECORD
