Metadata-Version: 2.4
Name: iflow-mcp_gustavo-meilus_logseq-api-mcp
Version: 0.1.0
Summary: Add your description here
Requires-Python: >=3.11
License-File: LICENSE
Requires-Dist: aiohttp>=3.12.14
Requires-Dist: load-dotenv>=0.1.0
Requires-Dist: mcp[cli]>=1.10.0
Requires-Dist: pathlib>=1.0.1
Requires-Dist: starlette>=0.47.2
Dynamic: license-file
